webframework/__init__.py
webframework/core/__init__.py
webframework/core/capabilites.py
webframework/core/webdriver.py
webframework/setting.py
webframework/utils.py
webframework/web/__init__.py
webframework/web/element.py
webframework/web/webelement.py
webframework-0.2.2.dist-info/WHEEL
webframework-0.2.2.dist-info/METADATA
webframework-0.2.2.dist-info/RECORD
